fosanalysis/__init__.py
fosanalysis/protocols.py
fosanalysis/compensation/__init__.py
fosanalysis/compensation/compensator.py
fosanalysis/compensation/shrinking.py
fosanalysis/compensation/tensionstiffening.py
fosanalysis/crackmonitoring/__init__.py
fosanalysis/crackmonitoring/cracks.py
fosanalysis/crackmonitoring/finding.py
fosanalysis/crackmonitoring/separation.py
fosanalysis/crackmonitoring/strainprofile.py
fosanalysis/preprocessing/__init__.py
fosanalysis/preprocessing/base.py
fosanalysis/preprocessing/filtering.py
fosanalysis/preprocessing/masking.py
fosanalysis/preprocessing/repair.py
fosanalysis/preprocessing/resizing.py
fosanalysis/utils/__init__.py
fosanalysis/utils/base.py
fosanalysis/utils/cropping.py
fosanalysis/utils/integration.py
fosanalysis/utils/interpolation.py
fosanalysis/utils/misc.py
fosanalysis/utils/windows.py
fosanalysis-0.4.1.dist-info/licenses/LICENSE
fosanalysis-0.4.1.dist-info/METADATA
fosanalysis-0.4.1.dist-info/WHEEL
fosanalysis-0.4.1.dist-info/top_level.txt
fosanalysis-0.4.1.dist-info/RECORD
