Metadata-Version: 2.4
Name: fosanalysis
Version: 0.4.1
Summary: A framework to evaluate distributed fiber optic sensor data
Author-email: Bertram Richter <bertram.richter@tu-dresden.de>
Maintainer-email: Bertram Richter <bertram.richter@tu-dresden.de>
License:                     GNU GENERAL PUBLIC LICENSE
Project-URL: homepage, https://github.com/TUD-IMB/fosanalysis
Project-URL: source, https://github.com/TUD-IMB/fosanalysis
Project-URL: issues, https://github.com/TUD-IMB/fosanalysis/issues
Project-URL: changelog, https://github.com/TUD-IMB/fosanalysis/blob/master/CHANGELOG.md
Project-URL: documentation, https://tud-imb.github.io/fosanalysis/
Keywords: structural health monitoring,distributed fiber optic sensor,DFOS,data evaluation,distributed strain sensing,pre-processing,crack monitoring
Classifier: Intended Audience :: Developers
Classifier: Intended Audience :: Science/Research
Classifier: License :: OSI Approved :: GNU General Public License v3 (GPLv3)
Classifier: Programming Language :: Python :: 3
Classifier: Programming Language :: Python :: 3.9
Classifier: Programming Language :: Python :: 3.10
Classifier: Programming Language :: Python :: 3.11
Classifier: Programming Language :: Python :: 3.12
Classifier: Programming Language :: Python :: 3 :: Only
Requires-Python: >=3.7
License-File: LICENSE
Requires-Dist: numpy
Requires-Dist: scipy
Dynamic: license-file
